acfun_upload/__init__.py
acfun_upload/acfun.py
acfun_upload-0.0.3.dist-info/LICENSE
acfun_upload-0.0.3.dist-info/METADATA
acfun_upload-0.0.3.dist-info/WHEEL
acfun_upload-0.0.3.dist-info/top_level.txt
acfun_upload-0.0.3.dist-info/RECORD
