Metadata-Version: 2.1
Name: acfun-upload
Version: 0.0.3
Summary: AcFun 命令行投稿工具。Upload video to AcFun with Python.
Home-page: https://github.com/Aruelius/acfun_upload
Author: Aruelius
Author-email: aurelius@aliyun.com
License: GNU General Public License v3.0
Keywords: acfun,upload,acfun投稿,投稿脚本
Platform: UNKNOWN
Classifier: Programming Language :: Python :: 3.7
Classifier: License :: OSI Approved :: GNU General Public License v3 (GPLv3)
Classifier: Topic :: Internet :: WWW/HTTP
Requires-Python: >=3.6
Requires-Dist: requests
